benfords_law_utils/__init__.py
benfords_law_utils/utils.py
benfords_law_utils-0.0.2.dist-info/LICENSE
benfords_law_utils-0.0.2.dist-info/METADATA
benfords_law_utils-0.0.2.dist-info/WHEEL
benfords_law_utils-0.0.2.dist-info/top_level.txt
benfords_law_utils-0.0.2.dist-info/RECORD
