Metadata-Version: 2.1
Name: benfords-law-utils
Version: 0.0.2
Summary: Utilities for exploring Benford's Law
Home-page: https://github.com/AndrewLane/benfords-law-utils
Author: Andrew Lane
Author-email: andrew.w.lane@gmail.com
License: UNKNOWN
Platform: UNKNOWN
Classifier: Programming Language :: Python :: 3
Classifier: License :: OSI Approved :: MIT License
Classifier: Operating System :: OS Independent
Requires-Python: >=3.6
